mlxsummary/__init__.py
mlxsummary/cli.py
mlxsummary/formatters.py
mlxsummary/inspector.py
mlxsummary/summary.py
mlxsummary-0.1.0.dist-info/WHEEL
mlxsummary-0.1.0.dist-info/entry_points.txt
mlxsummary-0.1.0.dist-info/METADATA
mlxsummary-0.1.0.dist-info/RECORD
