Metadata-Version: 2.4
Name: mlxsummary
Version: 0.1.0
Summary: Model inspection and summary tools for MLX neural networks
Keywords: mlx,apple,machine-learning,deep-learning,neural-network,model-summary,pytorch-summary
Author: Dhruv Shrivastava
Author-email: Dhruv Shrivastava <dhruvshrivastava@hotmail.com>
License-Expression: MIT
Classifier: Development Status :: 4 - Beta
Classifier: Intended Audience :: Developers
Classifier: Intended Audience :: Science/Research
Classifier: License :: OSI Approved :: MIT License
Classifier: Operating System :: MacOS
Classifier: Programming Language :: Python :: 3
Classifier: Programming Language :: Python :: 3.9
Classifier: Programming Language :: Python :: 3.10
Classifier: Programming Language :: Python :: 3.11
Classifier: Programming Language :: Python :: 3.12
Classifier: Topic :: Scientific/Engineering :: Artificial Intelligence
Requires-Dist: mlx>=0.1.0
Requires-Dist: pytest>=7.0 ; extra == 'dev'
Requires-Dist: pytest-cov>=4.0 ; extra == 'dev'
Requires-Dist: black>=23.0 ; extra == 'dev'
Requires-Dist: ruff>=0.1.0 ; extra == 'dev'
Requires-Dist: mypy>=1.0 ; extra == 'dev'
Requires-Python: >=3.9
Project-URL: Documentation, https://github.com/dhruvshr/mlxsummary#readme
Project-URL: Homepage, https://github.com/dhruvshr/mlxsummary
Project-URL: Issues, https://github.com/dhruvshr/mlxsummary/issues
Project-URL: Repository, https://github.com/dhruvshr/mlxsummary
Provides-Extra: dev
